bizact_insights/__init__.py
bizact_insights/main.py
bizact_insights/prompts.py
bizact_insights-2025.12.21201957.dist-info/METADATA
bizact_insights-2025.12.21201957.dist-info/WHEEL
bizact_insights-2025.12.21201957.dist-info/top_level.txt
bizact_insights-2025.12.21201957.dist-info/RECORD
