Metadata-Version: 2.4
Name: bizact-insights
Version: 2025.12.21201957
Summary: Text input processor for corporate actions, extracting key entities, actions, and context.
Author-email: bizact-insights <hi@eugene.plus>
License: MIT
Project-URL: Homepage, https://github.com/chigwell/bizact-insights
Requires-Python: >=3.9
Requires-Dist: langchain-llm7>=0.0.0
Requires-Dist: llmatch-messages>=0.0.0
Requires-Dist: langchain-core>=0.3.0
